pushgateway_py_client/__init__.py
pushgateway_py_client-0.4.1.dist-info/LICENSE
pushgateway_py_client-0.4.1.dist-info/METADATA
pushgateway_py_client-0.4.1.dist-info/WHEEL
pushgateway_py_client-0.4.1.dist-info/RECORD
