Metadata-Version: 2.1
Name: pushgateway-py-client
Version: 0.4.1
Summary: 
Author: Carl Kristensen
Author-email: cjckris@gmail.com
Requires-Python: >=3.11,<4.0
Classifier: Programming Language :: Python :: 3
Classifier: Programming Language :: Python :: 3.11
Requires-Dist: black (>=23.3.0,<24.0.0)
Requires-Dist: prometheus-client (==0.16.0)
Requires-Dist: pytest (>=7.3.1,<8.0.0)
